{
  "parent": "minecraft:recipes/root",
  "rewards": {
    "recipes": [
      "notenoughfoxes:white_green_collar"
    ]
  },
  "criteria": {
    "has_collar": {
      "trigger": "minecraft:inventory_changed",
      "conditions": {
        "items": [
          {
            "items": [
              "notenoughfoxes:white_collar"
            ]
          }
        ]
      }
    },
    "has_the_recipe": {
      "trigger": "minecraft:recipe_unlocked",
      "conditions": {
        "recipe": "notenoughfoxes:white_green_collar"
      }
    }
  },
  "requirements": [
    [
      "has_collar",
      "has_the_recipe"
    ]
  ]
}